DYAMS/__init__.py
DYAMS/client.py
DYAMS/enums.py
DYAMS/api/__init__.py
DYAMS/api/get_post_investment_product_asset_allocation.py
DYAMS/api/get_post_investment_product_holdings.py
DYAMS/api/get_post_investment_product_list.py
DYAMS/api/get_post_investment_product_net.py
DYAMS/api/get_post_investment_product_performance_indicators.py
DYAMS/api/get_private_asset_net.py
DYAMS/api/heartbeat.py
DYAMS/api/util.py
dyams-0.8.dist-info/licenses/LICENSE
dyams-0.8.dist-info/METADATA
dyams-0.8.dist-info/WHEEL
dyams-0.8.dist-info/top_level.txt
dyams-0.8.dist-info/RECORD
