Metadata-Version: 2.4
Name: DYAMS
Version: 0.8
Summary: 通联数据AMS系统数据SDK
Author-email: songjiangduo <jiangduo.song@datayes.com>
License-Expression: MIT
Classifier: Programming Language :: Python :: 3
Classifier: Operating System :: OS Independent
Requires-Python: >=3.6
License-File: LICENSE
Dynamic: license-file
